<?xml version="1.0" encoding="utf-8" ?>
<dwsync>
<file name="usa_tweets000.csv" server="200.98.64.22//" local="133305437050000000" remote="133305437050000000" />
<file name="usa_tweets001.csv" server="200.98.64.22//" local="133305437050000000" remote="133305437050000000" />
<file name="usa_tweets002.csv" server="200.98.64.22//" local="133305437050000000" remote="133305437050000000" />
<file name="usa_tweets003.csv" server="200.98.64.22//" local="133305437060000000" remote="133305437060000000" />
<file name="usa_tweets004.csv" server="200.98.64.22//" local="133305437060000000" remote="133305437060000000" />
<file name="usa_tweets005.csv" server="200.98.64.22//" local="133305437060000000" remote="133305437060000000" />
<file name="usa_tweets006.csv" server="200.98.64.22//" local="133305437060000000" remote="133305437060000000" />
<file name="usa_tweets007.csv" server="200.98.64.22//" local="133305437060000000" remote="133305437060000000" />
<file name="usa_tweets008.csv" server="200.98.64.22//" local="133305437060000000" remote="133305437060000000" />
<file name="usa_tweets009.csv" server="200.98.64.22//" local="133305437070000000" remote="133305437070000000" />
<file name="usa_tweets010.csv" server="200.98.64.22//" local="133305437070000000" remote="133305437070000000" />
<file name="usa_tweets011.csv" server="200.98.64.22//" local="133305437070000000" remote="133305437070000000" />
<file name="usa_tweets012.csv" server="200.98.64.22//" local="133305437070000000" remote="133305437070000000" />
<file name="usa_tweets013.csv" server="200.98.64.22//" local="133305437070000000" remote="133305437070000000" />
<file name="usa_tweets014.csv" server="200.98.64.22//" local="133305437070000000" remote="133305437070000000" />
<file name="usa_tweets015.csv" server="200.98.64.22//" local="133305437070000000" remote="133305437070000000" />
<file name="usa_tweets016.csv" server="200.98.64.22//" local="133305437080000000" remote="133305437080000000" />
<file name="usa_tweets017.csv" server="200.98.64.22//" local="133305437080000000" remote="133305437080000000" />
<file name="usa_tweets018.csv" server="200.98.64.22//" local="133305437080000000" remote="133305437080000000" />
<file name="usa_tweets019.csv" server="200.98.64.22//" local="133305437080000000" remote="133305437080000000" />
<file name="usa_tweets020.csv" server="200.98.64.22//" local="133305437080000000" remote="133305437080000000" />
<file name="usa_tweets021.csv" server="200.98.64.22//" local="133305437090000000" remote="133305437090000000" />
<file name="usa_tweets022.csv" server="200.98.64.22//" local="133305437090000000" remote="133305437090000000" />
<file name="usa_tweets023.csv" server="200.98.64.22//" local="133305437090000000" remote="133305437090000000" />
<file name="usa_tweets024.csv" server="200.98.64.22//" local="133305437090000000" remote="133305437090000000" />
<file name="usa_tweets025.csv" server="200.98.64.22//" local="133305437100000000" remote="133305437100000000" />
<file name="usa_tweets026.csv" server="200.98.64.22//" local="133305437100000000" remote="133305437100000000" />
<file name="usa_tweets027.csv" server="200.98.64.22//" local="133305437100000000" remote="133305437100000000" />
<file name="usa_tweets028.csv" server="200.98.64.22//" local="133305437100000000" remote="133305437100000000" />
<file name="usa_tweets029.csv" server="200.98.64.22//" local="133305437100000000" remote="133305437100000000" />
<file name="usa_tweets030.csv" server="200.98.64.22//" local="133305437100000000" remote="133305437100000000" />
<file name="usa_tweets031.csv" server="200.98.64.22//" local="133305437110000000" remote="133305437110000000" />
<file name="usa_tweets032.csv" server="200.98.64.22//" local="133305437110000000" remote="133305437110000000" />
<file name="usa_tweets033.csv" server="200.98.64.22//" local="133305437110000000" remote="133305437110000000" />
<file name="usa_tweets034.csv" server="200.98.64.22//" local="133305437110000000" remote="133305437110000000" />
<file name="usa_tweets035.csv" server="200.98.64.22//" local="133305437110000000" remote="133305437110000000" />
<file name="usa_tweets036.csv" server="200.98.64.22//" local="133305437110000000" remote="133305437110000000" />
<file name="usa_tweets037.csv" server="200.98.64.22//" local="133305437120000000" remote="133305437120000000" />
<file name="usa_tweets038.csv" server="200.98.64.22//" local="133305437120000000" remote="133305437120000000" />
<file name="usa_tweets039.csv" server="200.98.64.22//" local="133305437130000000" remote="133305437130000000" />
<file name="usa_tweets040.csv" server="200.98.64.22//" local="133305437130000000" remote="133305437130000000" />
<file name="usa_tweets041.csv" server="200.98.64.22//" local="133305437130000000" remote="133305437130000000" />
<file name="usa_tweets042.csv" server="200.98.64.22//" local="133305437130000000" remote="133305437130000000" />
<file name="usa_tweets043.csv" server="200.98.64.22//" local="133305437130000000" remote="133305437130000000" />
<file name="usa_tweets044.csv" server="200.98.64.22//" local="133305437130000000" remote="133305437130000000" />
<file name="usa_tweets045.csv" server="200.98.64.22//" local="133305437140000000" remote="133305437140000000" />
<file name="usa_tweets046.csv" server="200.98.64.22//" local="133305437140000000" remote="133305437140000000" />
<file name="usa_tweets047.csv" server="200.98.64.22//" local="133305437140000000" remote="133305437140000000" />
<file name="usa_tweets048.csv" server="200.98.64.22//" local="133305437150000000" remote="133305437150000000" />
<file name="usa_tweets049.csv" server="200.98.64.22//" local="133305437150000000" remote="133305437150000000" />
<file name="usa_tweets050.csv" server="200.98.64.22//" local="133305437150000000" remote="133305437150000000" />
<file name="usa_tweets051.csv" server="200.98.64.22//" local="133305437150000000" remote="133305437150000000" />
<file name="usa_tweets052.csv" server="200.98.64.22//" local="133305437150000000" remote="133305437150000000" />
<file name="usa_tweets053.csv" server="200.98.64.22//" local="133305437150000000" remote="133305437150000000" />
<file name="usa_tweets054.csv" server="200.98.64.22//" local="133305437160000000" remote="133305437160000000" />
<file name="usa_tweets055.csv" server="200.98.64.22//" local="133305437160000000" remote="133305437160000000" />
<file name="usa_tweets056.csv" server="200.98.64.22//" local="133305437160000000" remote="133305437160000000" />
<file name="usa_tweets057.csv" server="200.98.64.22//" local="133305437160000000" remote="133305437160000000" />
<file name="usa_tweets058.csv" server="200.98.64.22//" local="133305437160000000" remote="133305437160000000" />
<file name="usa_tweets059.csv" server="200.98.64.22//" local="133305437160000000" remote="133305437160000000" />
<file name="usa_tweets060.csv" server="200.98.64.22//" local="133305437170000000" remote="133305437170000000" />
<file name="usa_tweets061.csv" server="200.98.64.22//" local="133305437170000000" remote="133305437170000000" />
<file name="usa_tweets062.csv" server="200.98.64.22//" local="133305437170000000" remote="133305437170000000" />
<file name="usa_tweets063.csv" server="200.98.64.22//" local="133305437170000000" remote="133305437170000000" />
<file name="usa_tweets064.csv" server="200.98.64.22//" local="133305437170000000" remote="133305437170000000" />
<file name="usa_tweets065.csv" server="200.98.64.22//" local="133305437170000000" remote="133305437170000000" />
<file name="usa_tweets066.csv" server="200.98.64.22//" local="133305437180000000" remote="133305437180000000" />
<file name="usa_tweets067.csv" server="200.98.64.22//" local="133305437180000000" remote="133305437180000000" />
<file name="usa_tweets068.csv" server="200.98.64.22//" local="133305437180000000" remote="133305437180000000" />
<file name="usa_tweets069.csv" server="200.98.64.22//" local="133305437180000000" remote="133305437180000000" />
<file name="usa_tweets070.csv" server="200.98.64.22//" local="133305437180000000" remote="133305437180000000" />
<file name="usa_tweets071.csv" server="200.98.64.22//" local="133305437180000000" remote="133305437180000000" />
<file name="usa_tweets072.csv" server="200.98.64.22//" local="133305437190000000" remote="133305437190000000" />
<file name="usa_tweets073.csv" server="200.98.64.22//" local="133305437190000000" remote="133305437190000000" />
<file name="usa_tweets074.csv" server="200.98.64.22//" local="133305437190000000" remote="133305437190000000" />
<file name="usa_tweets075.csv" server="200.98.64.22//" local="133305437190000000" remote="133305437190000000" />
<file name="usa_tweets076.csv" server="200.98.64.22//" local="133305437190000000" remote="133305437190000000" />
<file name="usa_tweets077.csv" server="200.98.64.22//" local="133305437200000000" remote="133305437200000000" />
<file name="usa_tweets078.csv" server="200.98.64.22//" local="133305437200000000" remote="133305437200000000" />
<file name="usa_tweets079.csv" server="200.98.64.22//" local="133305437200000000" remote="133305437200000000" />
<file name="usa_tweets080.csv" server="200.98.64.22//" local="133305437200000000" remote="133305437200000000" />
<file name="usa_tweets081.csv" server="200.98.64.22//" local="133305437200000000" remote="133305437200000000" />
<file name="usa_tweets082.csv" server="200.98.64.22//" local="133305437200000000" remote="133305437200000000" />
<file name="usa_tweets083.csv" server="200.98.64.22//" local="133305437200000000" remote="133305437200000000" />
<file name="usa_tweets084.csv" server="200.98.64.22//" local="133305437210000000" remote="133305437210000000" />
<file name="usa_tweets085.csv" server="200.98.64.22//" local="133305437210000000" remote="133305437210000000" />
<file name="usa_tweets086.csv" server="200.98.64.22//" local="133305437210000000" remote="133305437210000000" />
<file name="usa_tweets087.csv" server="200.98.64.22//" local="133305437210000000" remote="133305437210000000" />
<file name="usa_tweets088.csv" server="200.98.64.22//" local="133305437210000000" remote="133305437210000000" />
<file name="usa_tweets089.csv" server="200.98.64.22//" local="133305437210000000" remote="133305437210000000" />
<file name="usa_tweets090.csv" server="200.98.64.22//" local="133305437220000000" remote="133305437220000000" />
<file name="usa_tweets091.csv" server="200.98.64.22//" local="133305437220000000" remote="133305437220000000" />
<file name="usa_tweets092.csv" server="200.98.64.22//" local="133305437220000000" remote="133305437220000000" />
<file name="usa_tweets093.csv" server="200.98.64.22//" local="133305437220000000" remote="133305437220000000" />
<file name="usa_tweets094.csv" server="200.98.64.22//" local="133305437220000000" remote="133305437220000000" />
<file name="usa_tweets095.csv" server="200.98.64.22//" local="133305437220000000" remote="133305437220000000" />
<file name="usa_tweets096.csv" server="200.98.64.22//" local="133305437230000000" remote="133305437230000000" />
<file name="usa_tweets097.csv" server="200.98.64.22//" local="133305437230000000" remote="133305437230000000" />
<file name="usa_tweets098.csv" server="200.98.64.22//" local="133305437230000000" remote="133305437230000000" />
<file name="usa_tweets099.csv" server="200.98.64.22//" local="133305437230000000" remote="133305437230000000" />
<file name="usa_tweets100.csv" server="200.98.64.22//" local="133305437230000000" remote="133305437230000000" />
<file name="usa_tweets101.csv" server="200.98.64.22//" local="133305437240000000" remote="133305437240000000" />
<file name="usa_tweets102.csv" server="200.98.64.22//" local="133305437240000000" remote="133305437240000000" />
</dwsync>